{"errors":[],"warnings":[],"namedChunkGroups":{"app":{"chunks":[4,2,0],"assets":["webpack-runtime-5eee0a7a2d922b5d217c.js","webpack-runtime-5eee0a7a2d922b5d217c.js.map","framework-4d07bacc3808af3f4337.js","framework-4d07bacc3808af3f4337.js.map","app-6112900fc77723b5a840.js","app-6112900fc77723b5a840.js.map"],"children":{},"childAssets":{}},"component---src-pages-index-js":{"chunks":[3,1],"assets":["styles.eef1817f42bbc701704b.css","styles-dd3841a4888192e20843.js","styles-dd3841a4888192e20843.js.map","component---src-pages-index-js-2cced7f593b4b56857a1.js","component---src-pages-index-js-2cced7f593b4b56857a1.js.map"],"children":{},"childAssets":{}}},"assetsByChunkName":{"app":["webpack-runtime-5eee0a7a2d922b5d217c.js","framework-4d07bacc3808af3f4337.js","app-6112900fc77723b5a840.js"],"component---src-pages-index-js":["styles.eef1817f42bbc701704b.css","styles-dd3841a4888192e20843.js","component---src-pages-index-js-2cced7f593b4b56857a1.js"]}}